Metadata-Version: 1.0
Name: army
Version: 0.1.1
Summary: Arm cross compiling toolset
Home-page: https://github.com/turdusmerula/army/
Author: Sebastien Besombes
Author-email: UNKNOWN
License: GPLv3
Platform: UNKNOWN
